prometheus_mysql_exporter/__init__.py
prometheus_mysql_exporter/__main__.py
prometheus_mysql_exporter/metrics.py
prometheus_mysql_exporter/parser.py
prometheus_mysql_exporter/scheduler.py
prometheus_mysql_exporter/utils.py
prometheus_mysql_exporter-0.5.0.dist-info/LICENSE
prometheus_mysql_exporter-0.5.0.dist-info/METADATA
prometheus_mysql_exporter-0.5.0.dist-info/WHEEL
prometheus_mysql_exporter-0.5.0.dist-info/entry_points.txt
prometheus_mysql_exporter-0.5.0.dist-info/top_level.txt
prometheus_mysql_exporter-0.5.0.dist-info/RECORD
